nflapi/__init__.py
nflapi/version.py
nflapi-1.0.2.dist-info/LICENSE
nflapi-1.0.2.dist-info/METADATA
nflapi-1.0.2.dist-info/WHEEL
nflapi-1.0.2.dist-info/top_level.txt
nflapi-1.0.2.dist-info/RECORD
