Metadata-Version: 2.1
Name: nflapi
Version: 1.0.2
Summary: Python Wrapper for NFL API
Home-page: https://github.com/toddrob99/nflapi
Author: Todd Roberts
Author-email: todd@toddrob.com
License: UNKNOWN
Platform: UNKNOWN
Classifier: Programming Language :: Python
Classifier: Programming Language :: Python :: 3.8
Classifier: License :: OSI Approved :: MIT License
Classifier: Operating System :: OS Independent
Requires-Dist: requests
